setup.py
mysqlutil/DBUtil.py
mysqlutil/__init__.py
mysqlutil.egg-info/PKG-INFO
mysqlutil.egg-info/SOURCES.txt
mysqlutil.egg-info/dependency_links.txt
mysqlutil.egg-info/top_level.txt