Metadata-Version: 1.0
Name: mysqlutil
Version: 1.0.2
Summary: util for mysql
Home-page: UNKNOWN
Author: UNKNOWN
Author-email: UNKNOWN
License: MIT
Platform: UNKNOWN
